SMART/DMC_Calling.py
SMART/DeNovoDMR_Calling.py
SMART/Folderprocess.py
SMART/MethyMergeEntropy.py
SMART/NewEntropy.py
SMART/NewEntropyNormal.py
SMART/SMART.py
SMART/Segmentation.py
SMART/__init__.py
SMART/Example/Case_control_matrix.txt
SMART/Example/CpGisland_hg19.bed
SMART/Example/MethylMatrix_Test.txt
SMART_BS_Seq-2.2.8.data/scripts/SMART
SMART_BS_Seq-2.2.8.dist-info/DESCRIPTION.rst
SMART_BS_Seq-2.2.8.dist-info/METADATA
SMART_BS_Seq-2.2.8.dist-info/RECORD
SMART_BS_Seq-2.2.8.dist-info/WHEEL
SMART_BS_Seq-2.2.8.dist-info/metadata.json
SMART_BS_Seq-2.2.8.dist-info/top_level.txt
