Metadata-Version: 2.0
Name: SMART-BS-Seq
Version: 2.2.8
Summary: Specific Methylation Analysis and Report Tool 2
Home-page: http://fame.edbc.org/smart/
Author: Hongbo Liu
Author-email: hongbo919@gmail.com
License: UNKNOWN
Platform: UNKNOWN
Classifier: Development Status :: 5 - Production/Stable
Classifier: Programming Language :: Python :: 2.7
Classifier: License :: OSI Approved :: BSD License
Classifier: Intended Audience :: End Users/Desktop
Classifier: Operating System :: POSIX :: Linux
Classifier: Operating System :: MacOS
Requires-Dist: numpy (>=1.11.2)
Requires-Dist: pandas (==0.19.2)
Requires-Dist: scipy (>=0.18.1)
Requires-Dist: statsmodels (>=0.8.0)
